great_dataset/__init__.py
great_dataset/function_set.py
thisismygreatdataset-0.0.4.dist-info/LICENSE
thisismygreatdataset-0.0.4.dist-info/METADATA
thisismygreatdataset-0.0.4.dist-info/WHEEL
thisismygreatdataset-0.0.4.dist-info/top_level.txt
thisismygreatdataset-0.0.4.dist-info/RECORD
