Metadata-Version: 2.1
Name: thisismygreatdataset
Version: 0.0.4
Summary: a package to load my own dataset
Home-page: https://github.com/zemengchuan/thegreatdataset
Author: zemengchuan
Author-email: zemengchuan@gmail.com
License: MIT Licence
Project-URL: thegreatdataset, https://github.com/zemengchuan/thegreatdataset
Platform: any
Classifier: Programming Language :: Python :: 3
Classifier: License :: OSI Approved :: MIT License
Classifier: Operating System :: OS Independent
Requires-Python: >=3.5.0
License-File: LICENSE
Requires-Dist: pandas
